odoo/addons/partner_private_information/README.rst
odoo/addons/partner_private_information/__init__.py
odoo/addons/partner_private_information/__manifest__.py
odoo/addons/partner_private_information/i18n/es.po
odoo/addons/partner_private_information/models/__init__.py
odoo/addons/partner_private_information/models/res_partner.py
odoo/addons/partner_private_information/models/res_partner_category.py
odoo/addons/partner_private_information/readme/CONFIGURE.md
odoo/addons/partner_private_information/readme/CONTRIBUTORS.md
odoo/addons/partner_private_information/readme/DESCRIPTION.md
odoo/addons/partner_private_information/readme/USAGE.md
odoo/addons/partner_private_information/security/partner_private_information_security.xml
odoo/addons/partner_private_information/static/description/icon.png
odoo/addons/partner_private_information/static/description/index.html
odoo/addons/partner_private_information/tests/__init__.py
odoo/addons/partner_private_information/tests/test_partner_private_information.py
odoo/addons/partner_private_information/views/res_partner_category_views.xml
odoo/addons/partner_private_information/views/res_partner_view.xml
odoo_addon_partner_private_information-18.0.1.0.0.2.dist-info/METADATA
odoo_addon_partner_private_information-18.0.1.0.0.2.dist-info/WHEEL
odoo_addon_partner_private_information-18.0.1.0.0.2.dist-info/top_level.txt
odoo_addon_partner_private_information-18.0.1.0.0.2.dist-info/RECORD
